primp-0.14.0.dist-info/METADATA
primp-0.14.0.dist-info/WHEEL
primp-0.14.0.dist-info/licenses/LICENSE
primp/__init__.py
primp/py.typed
primp/primp.pyi
primp/primp.abi3.so
primp-0.14.0.dist-info/RECORD
