Metadata-Version: 2.4
Name: primp
Version: 0.14.0
Classifier: Programming Language :: Rust
Classifier: Programming Language :: Python :: 3
Classifier: Programming Language :: Python :: 3 :: Only
Classifier: Programming Language :: Python :: 3.8
Classifier: Programming Language :: Python :: 3.9
Classifier: Programming Language :: Python :: 3.10
Classifier: Programming Language :: Python :: 3.11
Classifier: Programming Language :: Python :: 3.12
Classifier: Programming Language :: Python :: 3.13
Classifier: Programming Language :: Python :: Implementation :: CPython
Classifier: Programming Language :: Python :: Implementation :: PyPy
Classifier: Topic :: Internet :: WWW/HTTP
Classifier: Topic :: Software Development :: Libraries :: Python Modules
Requires-Dist: certifi ; extra == 'dev'
Requires-Dist: pytest>=8.1.1 ; extra == 'dev'
Requires-Dist: pytest-asyncio>=0.25.3 ; extra == 'dev'
Requires-Dist: typing-extensions ; python_full_version < '3.12' and extra == 'dev'
Requires-Dist: mypy>=1.14.1 ; extra == 'dev'
Requires-Dist: ruff>=0.9.2 ; extra == 'dev'
Provides-Extra: dev
License-File: LICENSE
Summary: HTTP client that can impersonate web browsers, mimicking their headers and `TLS/JA3/JA4/HTTP2` fingerprints
Keywords: python,request,impersonate
Author: deedy5
License: MIT License
Requires-Python: >=3.8
